[{"line":2,"elements":[{"start_timestamp":"2022-02-06T21:00:35.066Z","before":[{"result":{"duration":8005100,"status":"passed"},"match":{"location":"stepdefination.Hooks.setUp()"}}],"line":22,"name":"TC13 Edito sayfasina farkli kisiler ekleme","description":"","id":"us1009-editor-sayfasinda-giris-yapilabildigini-test-et;tc13-edito-sayfasina-farkli-kisiler-ekleme;;2","after":[{"result":{"duration":13608677800,"status":"passed"},"match":{"location":"stepdefination.Hooks.tearDown(io.cucumber.java.Scenario)"}}],"type":"scenario","keyword":"Scenario Outline","steps":[{"result":{"duration":9502452000,"status":"passed"},"line":6,"name":"kullanici \"editorUrl\" sayfasina gider","match":{"arguments":[{"val":"\"editorUrl\"","offset":10}],"location":"stepdefination.amazonStepDefination.kullaniciSayfasinaGider(java.lang.String)"},"keyword":"Given "},{"result":{"duration":245996400,"status":"passed"},"line":7,"name":"new butonuna basar","match":{"location":"stepdefination.Editor.datatableStepDefination.new_butonuna_basar()"},"keyword":"Then "},{"result":{"duration":218007700,"status":"passed"},"line":8,"name":"editor firstname kutusuna \"Hakan\" bilgileri girer","match":{"arguments":[{"val":"\"Hakan\"","offset":26}],"location":"stepdefination.Editor.datatableStepDefination.editor_firstname_kutusuna_bilgileri_girer(java.lang.String)"},"keyword":"And "},{"result":{"duration":206999700,"status":"passed"},"line":9,"name":"editor lastname kutusuna \"Tetik\" bilgileri girer","match":{"arguments":[{"val":"\"Tetik\"","offset":25}],"location":"stepdefination.Editor.datatableStepDefination.editor_lastname_kutusuna_bilgileri_girer(java.lang.String)"},"keyword":"And "},{"result":{"duration":188994300,"status":"passed"},"line":10,"name":"editor position kutusuna \"TestLead\" bilgileri girer","match":{"arguments":[{"val":"\"TestLead\"","offset":25}],"location":"stepdefination.Editor.datatableStepDefination.editor_position_kutusuna_bilgileri_girer(java.lang.String)"},"keyword":"And "},{"result":{"duration":122009100,"status":"passed"},"line":11,"name":"editor office kutusuna \"Paris\" bilgileri girer","match":{"arguments":[{"val":"\"Paris\"","offset":23}],"location":"stepdefination.Editor.datatableStepDefination.editor_office_kutusuna_bilgileri_girer(java.lang.String)"},"keyword":"And "},{"result":{"duration":122998300,"status":"passed"},"line":12,"name":"editor extension kutusuna \"ali\" bilgileri girer","match":{"arguments":[{"val":"\"ali\"","offset":26}],"location":"stepdefination.Editor.datatableStepDefination.editor_extension_kutusuna_bilgileri_girer(java.lang.String)"},"keyword":"And "},{"result":{"duration":277002100,"status":"passed"},"line":13,"name":"editor startdate kutusuna \"2021-01-21\" bilgileri girer","match":{"arguments":[{"val":"\"2021-01-21\"","offset":26}],"location":"stepdefination.Editor.datatableStepDefination.editor_startdate_kutusuna_bilgileri_girer(java.lang.String)"},"keyword":"And "},{"result":{"duration":111002800,"status":"passed"},"line":14,"name":"editor salary kutusuna \"60000\" bilgileri girer","match":{"arguments":[{"val":"\"60000\"","offset":23}],"location":"stepdefination.Editor.datatableStepDefination.editor_salary_kutusuna_bilgileri_girer(java.lang.String)"},"keyword":"And "},{"result":{"duration":144999900,"status":"passed"},"line":15,"name":"Create tusuna basar","match":{"location":"stepdefination.Editor.datatableStepDefination.create_tusuna_basar()"},"keyword":"And "},{"result":{"duration":3298412300,"status":"passed"},"line":16,"name":"\"Hakan\" ve \"Tetik\" girerek kaydin tamamlandigini test eder","match":{"arguments":[{"val":"\"Hakan\"","offset":0},{"val":"\"Tetik\"","offset":11}],"location":"stepdefination.Editor.datatableStepDefination.veGirerekKaydinTamamlandiginiTestEder(java.lang.String,java.lang.String)"},"keyword":"Then "},{"result":{"duration":10580883400,"status":"passed"},"line":17,"name":"sayfayi kapatir","match":{"location":"stepdefination.amazonStepDefination.sayfayi_kapatir()"},"keyword":"And "}],"tags":[{"name":"@Paralel2"},{"name":"@editor3"}]},{"start_timestamp":"2022-02-06T21:01:14.190Z","before":[{"result":{"status":"passed"},"match":{"location":"stepdefination.Hooks.setUp()"}}],"line":23,"name":"TC13 Edito sayfasina farkli kisiler ekleme","description":"","id":"us1009-editor-sayfasinda-giris-yapilabildigini-test-et;tc13-edito-sayfasina-farkli-kisiler-ekleme;;3","after":[{"result":{"duration":8872824600,"status":"passed"},"match":{"location":"stepdefination.Hooks.tearDown(io.cucumber.java.Scenario)"}}],"type":"scenario","keyword":"Scenario Outline","steps":[{"result":{"duration":3506983300,"status":"passed"},"line":6,"name":"kullanici \"editorUrl\" sayfasina gider","match":{"arguments":[{"val":"\"editorUrl\"","offset":10}],"location":"stepdefination.amazonStepDefination.kullaniciSayfasinaGider(java.lang.String)"},"keyword":"Given "},{"result":{"duration":153995200,"status":"passed"},"line":7,"name":"new butonuna basar","match":{"location":"stepdefination.Editor.datatableStepDefination.new_butonuna_basar()"},"keyword":"Then "},{"result":{"duration":201027800,"status":"passed"},"line":8,"name":"editor firstname kutusuna \"Murat\" bilgileri girer","match":{"arguments":[{"val":"\"Murat\"","offset":26}],"location":"stepdefination.Editor.datatableStepDefination.editor_firstname_kutusuna_bilgileri_girer(java.lang.String)"},"keyword":"And "},{"result":{"duration":208015500,"status":"passed"},"line":9,"name":"editor lastname kutusuna \"Ercoban\" bilgileri girer","match":{"arguments":[{"val":"\"Ercoban\"","offset":25}],"location":"stepdefination.Editor.datatableStepDefination.editor_lastname_kutusuna_bilgileri_girer(java.lang.String)"},"keyword":"And "},{"result":{"duration":132997800,"status":"passed"},"line":10,"name":"editor position kutusuna \"QA\" bilgileri girer","match":{"arguments":[{"val":"\"QA\"","offset":25}],"location":"stepdefination.Editor.datatableStepDefination.editor_position_kutusuna_bilgileri_girer(java.lang.String)"},"keyword":"And "},{"result":{"duration":168018000,"status":"passed"},"line":11,"name":"editor office kutusuna \"Kenya\" bilgileri girer","match":{"arguments":[{"val":"\"Kenya\"","offset":23}],"location":"stepdefination.Editor.datatableStepDefination.editor_office_kutusuna_bilgileri_girer(java.lang.String)"},"keyword":"And "},{"result":{"duration":141002300,"status":"passed"},"line":12,"name":"editor extension kutusuna \"126\" bilgileri girer","match":{"arguments":[{"val":"\"126\"","offset":26}],"location":"stepdefination.Editor.datatableStepDefination.editor_extension_kutusuna_bilgileri_girer(java.lang.String)"},"keyword":"And "},{"result":{"duration":367999100,"status":"passed"},"line":13,"name":"editor startdate kutusuna \"2021-01-20\" bilgileri girer","match":{"arguments":[{"val":"\"2021-01-20\"","offset":26}],"location":"stepdefination.Editor.datatableStepDefination.editor_startdate_kutusuna_bilgileri_girer(java.lang.String)"},"keyword":"And "},{"result":{"duration":154998300,"status":"passed"},"line":14,"name":"editor salary kutusuna \"40000\" bilgileri girer","match":{"arguments":[{"val":"\"40000\"","offset":23}],"location":"stepdefination.Editor.datatableStepDefination.editor_salary_kutusuna_bilgileri_girer(java.lang.String)"},"keyword":"And "},{"result":{"duration":155986000,"status":"passed"},"line":15,"name":"Create tusuna basar","match":{"location":"stepdefination.Editor.datatableStepDefination.create_tusuna_basar()"},"keyword":"And "},{"result":{"duration":3370366800,"status":"passed"},"line":16,"name":"\"Murat\" ve \"Ercoban\" girerek kaydin tamamlandigini test eder","match":{"arguments":[{"val":"\"Murat\"","offset":0},{"val":"\"Ercoban\"","offset":11}],"location":"stepdefination.Editor.datatableStepDefination.veGirerekKaydinTamamlandiginiTestEder(java.lang.String,java.lang.String)"},"keyword":"Then "},{"result":{"duration":10441251500,"status":"passed"},"line":17,"name":"sayfayi kapatir","match":{"location":"stepdefination.amazonStepDefination.sayfayi_kapatir()"},"keyword":"And "}],"tags":[{"name":"@Paralel2"},{"name":"@editor3"}]},{"start_timestamp":"2022-02-06T21:01:42.137Z","before":[{"result":{"status":"passed"},"match":{"location":"stepdefination.Hooks.setUp()"}}],"line":24,"name":"TC13 Edito sayfasina farkli kisiler ekleme","description":"","id":"us1009-editor-sayfasinda-giris-yapilabildigini-test-et;tc13-edito-sayfasina-farkli-kisiler-ekleme;;4","after":[{"result":{"duration":8604806000,"status":"passed"},"match":{"location":"stepdefination.Hooks.tearDown(io.cucumber.java.Scenario)"}}],"type":"scenario","keyword":"Scenario Outline","steps":[{"result":{"duration":3790555300,"status":"passed"},"line":6,"name":"kullanici \"editorUrl\" sayfasina gider","match":{"arguments":[{"val":"\"editorUrl\"","offset":10}],"location":"stepdefination.amazonStepDefination.kullaniciSayfasinaGider(java.lang.String)"},"keyword":"Given "},{"result":{"duration":179999600,"status":"passed"},"line":7,"name":"new butonuna basar","match":{"location":"stepdefination.Editor.datatableStepDefination.new_butonuna_basar()"},"keyword":"Then "},{"result":{"duration":190997200,"status":"passed"},"line":8,"name":"editor firstname kutusuna \"Furkan\" bilgileri girer","match":{"arguments":[{"val":"\"Furkan\"","offset":26}],"location":"stepdefination.Editor.datatableStepDefination.editor_firstname_kutusuna_bilgileri_girer(java.lang.String)"},"keyword":"And "},{"result":{"duration":190003600,"status":"passed"},"line":9,"name":"editor lastname kutusuna \"Yilmaz\" bilgileri girer","match":{"arguments":[{"val":"\"Yilmaz\"","offset":25}],"location":"stepdefination.Editor.datatableStepDefination.editor_lastname_kutusuna_bilgileri_girer(java.lang.String)"},"keyword":"And "},{"result":{"duration":220993100,"status":"passed"},"line":10,"name":"editor position kutusuna \"QA\" bilgileri girer","match":{"arguments":[{"val":"\"QA\"","offset":25}],"location":"stepdefination.Editor.datatableStepDefination.editor_position_kutusuna_bilgileri_girer(java.lang.String)"},"keyword":"And "},{"result":{"duration":125996700,"status":"passed"},"line":11,"name":"editor office kutusuna \"Adana\" bilgileri girer","match":{"arguments":[{"val":"\"Adana\"","offset":23}],"location":"stepdefination.Editor.datatableStepDefination.editor_office_kutusuna_bilgileri_girer(java.lang.String)"},"keyword":"And "},{"result":{"duration":119999200,"status":"passed"},"line":12,"name":"editor extension kutusuna \"130\" bilgileri girer","match":{"arguments":[{"val":"\"130\"","offset":26}],"location":"stepdefination.Editor.datatableStepDefination.editor_extension_kutusuna_bilgileri_girer(java.lang.String)"},"keyword":"And "},{"result":{"duration":282999500,"status":"passed"},"line":13,"name":"editor startdate kutusuna \"2021-03-21\" bilgileri girer","match":{"arguments":[{"val":"\"2021-03-21\"","offset":26}],"location":"stepdefination.Editor.datatableStepDefination.editor_startdate_kutusuna_bilgileri_girer(java.lang.String)"},"keyword":"And "},{"result":{"duration":131998800,"status":"passed"},"line":14,"name":"editor salary kutusuna \"80000\" bilgileri girer","match":{"arguments":[{"val":"\"80000\"","offset":23}],"location":"stepdefination.Editor.datatableStepDefination.editor_salary_kutusuna_bilgileri_girer(java.lang.String)"},"keyword":"And "},{"result":{"duration":125007800,"status":"passed"},"line":15,"name":"Create tusuna basar","match":{"location":"stepdefination.Editor.datatableStepDefination.create_tusuna_basar()"},"keyword":"And "},{"result":{"duration":3363125700,"status":"passed"},"line":16,"name":"\"Furkan\" ve \"Yilmaz\" girerek kaydin tamamlandigini test eder","match":{"arguments":[{"val":"\"Furkan\"","offset":0},{"val":"\"Yilmaz\"","offset":12}],"location":"stepdefination.Editor.datatableStepDefination.veGirerekKaydinTamamlandiginiTestEder(java.lang.String,java.lang.String)"},"keyword":"Then "},{"result":{"duration":10429408500,"status":"passed"},"line":17,"name":"sayfayi kapatir","match":{"location":"stepdefination.amazonStepDefination.sayfayi_kapatir()"},"keyword":"And "}],"tags":[{"name":"@Paralel2"},{"name":"@editor3"}]}],"name":"US1009 editor sayfasinda giris yapilabildigini test et","description":"","id":"us1009-editor-sayfasinda-giris-yapilabildigini-test-et","keyword":"Feature","uri":"file:src/test/resources/features/US1009_EditorCokluGirisTesti.feature","tags":[{"name":"@Paralel2","type":"Tag","location":{"line":1,"column":1}}]}]